README.rst
setup.py
TEDT/__init__.py
TEDT/candidate_corpus.py
TEDT/candidate_title.py
TEDT/corpus_decision_model.py
TEDT/information_extraction.py
TEDT/release_time.py
TEDT/segmentation.py
TEDT/stopwords.txt
TEDT/text_rank.py
TEDT/util.py
TEDT.egg-info/PKG-INFO
TEDT.egg-info/SOURCES.txt
TEDT.egg-info/dependency_links.txt
TEDT.egg-info/requires.txt
TEDT.egg-info/top_level.txt