Metadata-Version: 1.1
Name: TEDT
Version: 0.5
Summary: News Title Extraction Algorithm Based on Density and Text Features
Home-page: https://github.com/pzs741/TEDT
Author: ZhenSheng Peng
Author-email: pzsyjsgldd@163.com
License: MIT
Platform: UNKNOWN
Classifier: Programming Language :: Python :: 3
Classifier: Natural Language :: English
Classifier: Intended Audience :: Developers
